pyvision/__init__.py
pyvision/analysis/ImageLog.py
pyvision/analysis/Montage.py
pyvision/analysis/Table.py
pyvision/analysis/Timer.py
pyvision/analysis/__init__.py
pyvision/analysis/bee.py
pyvision/analysis/face.py
pyvision/analysis/gui_tools.py
pyvision/analysis/html_report.py
pyvision/analysis/plot.py
pyvision/analysis/progress_bar.py
pyvision/analysis/roc.py
pyvision/analysis/stats.py
pyvision/analysis/FaceAnalysis/EyeDetectionTest.py
pyvision/analysis/FaceAnalysis/EyesFile.py
pyvision/analysis/FaceAnalysis/FERET.py
pyvision/analysis/FaceAnalysis/FRGC2004.py
pyvision/analysis/FaceAnalysis/FaceDatabase.py
pyvision/analysis/FaceAnalysis/FaceDetectionTest.py
pyvision/analysis/FaceAnalysis/FaceRecognitionTest.py
pyvision/analysis/FaceAnalysis/__init__.py
pyvision/analysis/R/__init__.py
pyvision/analysis/classifier/ConfusionMatrix.py
pyvision/analysis/classifier/__init__.py
pyvision/beta/__init__.py
pyvision/beta/videotasks.py
pyvision/beta/vtm.py
pyvision/config/Arial.ttf
pyvision/config/EyeLocatorASEF128x128.fel
pyvision/config/__init__.py
pyvision/config/facedetector_celebdb1.xml
pyvision/config/facedetector_celebdb2.xml
pyvision/config/haarcascade_frontalface_alt.xml
pyvision/config/haarcascade_frontalface_alt2.xml
pyvision/config/haarcascade_frontalface_alt_tree.xml
pyvision/config/haarcascade_frontalface_default.xml
pyvision/config/haarcascade_fullbody.xml
pyvision/config/haarcascade_lowerbody.xml
pyvision/config/haarcascade_mcs_upperbody.xml
pyvision/config/haarcascade_upperbody.xml
pyvision/data/__init__.py
pyvision/data/csuScrapShots/00001aa.pgm
pyvision/data/csuScrapShots/00001ab.pgm
pyvision/data/csuScrapShots/00001ac.pgm
pyvision/data/csuScrapShots/00001ad.pgm
pyvision/data/csuScrapShots/00001ae.pgm
pyvision/data/csuScrapShots/00002aa.pgm
pyvision/data/csuScrapShots/00002ab.pgm
pyvision/data/csuScrapShots/00002ac.pgm
pyvision/data/csuScrapShots/00002ad.pgm
pyvision/data/csuScrapShots/00002ae.pgm
pyvision/data/csuScrapShots/00002af.pgm
pyvision_toolkit-1.3.6.dist-info/LICENSE
pyvision_toolkit-1.3.6.dist-info/LICENSE.txt
pyvision_toolkit-1.3.6.dist-info/METADATA
pyvision_toolkit-1.3.6.dist-info/WHEEL
pyvision_toolkit-1.3.6.dist-info/top_level.txt
pyvision_toolkit-1.3.6.dist-info/RECORD
